odoo/addons/l10n_th_withholding_tax/README.rst
odoo/addons/l10n_th_withholding_tax/__init__.py
odoo/addons/l10n_th_withholding_tax/__manifest__.py
odoo/addons/l10n_th_withholding_tax/i18n/l10n_th_withholding_tax.pot
odoo/addons/l10n_th_withholding_tax/models/__init__.py
odoo/addons/l10n_th_withholding_tax/models/account.py
odoo/addons/l10n_th_withholding_tax/models/account_move.py
odoo/addons/l10n_th_withholding_tax/models/account_payment.py
odoo/addons/l10n_th_withholding_tax/models/account_withholding_tax.py
odoo/addons/l10n_th_withholding_tax/models/product.py
odoo/addons/l10n_th_withholding_tax/readme/CONFIGURATION.rst
odoo/addons/l10n_th_withholding_tax/readme/CONTRIBUTORS.rst
odoo/addons/l10n_th_withholding_tax/readme/DESCRIPTION.rst
odoo/addons/l10n_th_withholding_tax/readme/USAGE.rst
odoo/addons/l10n_th_withholding_tax/security/ir.model.access.csv
odoo/addons/l10n_th_withholding_tax/static/description/icon.png
odoo/addons/l10n_th_withholding_tax/static/description/index.html
odoo/addons/l10n_th_withholding_tax/tests/__init__.py
odoo/addons/l10n_th_withholding_tax/tests/account_withholding_tax_test.xml
odoo/addons/l10n_th_withholding_tax/tests/test_withholding_tax.py
odoo/addons/l10n_th_withholding_tax/views/account_move_view.xml
odoo/addons/l10n_th_withholding_tax/views/account_payment_view.xml
odoo/addons/l10n_th_withholding_tax/views/account_view.xml
odoo/addons/l10n_th_withholding_tax/views/account_withholding_tax.xml
odoo/addons/l10n_th_withholding_tax/views/product_view.xml
odoo13_addon_l10n_th_withholding_tax-13.0.1.0.2.dist-info/METADATA
odoo13_addon_l10n_th_withholding_tax-13.0.1.0.2.dist-info/WHEEL
odoo13_addon_l10n_th_withholding_tax-13.0.1.0.2.dist-info/top_level.txt
odoo13_addon_l10n_th_withholding_tax-13.0.1.0.2.dist-info/RECORD
